tfs_seon_client/__init__.py
tfs_seon_client/factory/__init__.py
tfs_seon_client/factory/factory.py
tfs_seon_client/factory/service_enum.py
tfs_seon_client/service/__init__.py
tfs_seon_client/service/tfs_service.py
tfs_seon_client-2.0.7.dist-info/METADATA
tfs_seon_client-2.0.7.dist-info/WHEEL
tfs_seon_client-2.0.7.dist-info/top_level.txt
tfs_seon_client-2.0.7.dist-info/RECORD
